{
  "blockedBy": [
    "T-003"
  ],
  "claimedBySession": "efc26ffb-44b6-4cb2-88d4-d837f9c697c8",
  "completedDate": "2026-04-14",
  "createdDate": "2026-04-13",
  "description": "Build src/merger/dedup.ts. When multiple lenses report the same finding (same file, same line, same category), merge into one finding with the highest confidence and note contributing lenses. Merge by (file, line, category) tuple.",
  "id": "T-010",
  "order": 10,
  "phase": "merger",
  "status": "complete",
  "title": "Cross-lens deduplication",
  "type": "task"
}
